srspy/__init__.py
srspy/py.typed
srspy/records.py
srspy/runs.py
srspy-0.0.5.dist-info/METADATA
srspy-0.0.5.dist-info/WHEEL
srspy-0.0.5.dist-info/RECORD
