Metadata-Version: 2.1
Name: srspy
Version: 0.0.5
Summary: A package for simple experiment run tracing.
Project-URL: Homepage, https://github.com/nlandolfi/srspy
Author-email: "N. C. Landolfi" <crews.fixture.0f@icloud.com>
Classifier: License :: OSI Approved :: MIT License
Classifier: Operating System :: OS Independent
Classifier: Programming Language :: Python :: 3
Requires-Python: >=3.7
Requires-Dist: numpy
Requires-Dist: python-dateutil
